{
    "category" : [
        {
            "path" :"/recruiting/talent",
            "id":"talent",
            "title" : "Talent"
        },
        {
            "path" :"/recruiting/benefit",
            "id":"benefit",
            "title" : "Benefit"
        },
        {
            "path" :"/recruiting/recruit",
            "id":"recruit",
            "title" :"Jobs (Recruit)"
        }
    ],
    "talent": {
        "title" : "Talent",
        "image" : "talent.jpg" 
    },
    "benefit":{
        "title" : "Benefit",
        "image": "benefit.jpg"
    },
    "recruit": {
        "title" : "입사지원 & 채용공고"
    }
}